gwebsockets/__init__.py
gwebsockets/protocol.py
gwebsockets/server.py
gwebsockets-0.7.dist-info/DESCRIPTION.rst
gwebsockets-0.7.dist-info/METADATA
gwebsockets-0.7.dist-info/RECORD
gwebsockets-0.7.dist-info/WHEEL
gwebsockets-0.7.dist-info/metadata.json
gwebsockets-0.7.dist-info/top_level.txt
